SigProfilerExtractor/__init__.py
SigProfilerExtractor/estimate_best_solution.py
SigProfilerExtractor/nmf_cpu.py
SigProfilerExtractor/nmf_gpu.py
SigProfilerExtractor/sigpro.py
SigProfilerExtractor/sigprofilerextractor_cli.py
SigProfilerExtractor/subroutines.py
SigProfilerExtractor/version.py
SigProfilerExtractor/controllers/cli_controller.py
SigProfilerExtractor/data/CNVInput/Battenberg_test.tsv
SigProfilerExtractor/data/CSVInput/csv_example.csv
SigProfilerExtractor/data/MatObjInput/21_breast_WGS_substitutions.mat
SigProfilerExtractor/data/ReferenceFiles/CNV_features.tsv
SigProfilerExtractor/data/ReferenceFiles/CN_classes_dictionary.txt
SigProfilerExtractor/data/TextInput/Samples_CNV.txt
SigProfilerExtractor/data/TextInput/Samples_DBS.txt
SigProfilerExtractor/data/TextInput/Samples_ID.txt
SigProfilerExtractor/data/TextInput/Samples_SBS.txt
SigProfilerExtractor/data/TextInput/Samples_SV.txt
SigProfilerExtractor/data/VCFInput/PD3851a.vcf
SigProfilerExtractor/data/VCFInput/PD3890a.vcf
SigProfilerExtractor/data/VCFInput/PD3904a.vcf
SigProfilerExtractor/data/VCFInput/PD3905a.vcf
SigProfilerExtractor/data/VCFInput/PD3945a.vcf
sigprofilerextractor-1.2.6.dist-info/licenses/LICENSE.txt
sigprofilerextractor-1.2.6.dist-info/METADATA
sigprofilerextractor-1.2.6.dist-info/WHEEL
sigprofilerextractor-1.2.6.dist-info/entry_points.txt
sigprofilerextractor-1.2.6.dist-info/top_level.txt
sigprofilerextractor-1.2.6.dist-info/RECORD
