Metadata-Version: 2.4
Name: SigProfilerExtractor
Version: 1.2.6
Summary: Extracts mutational signatures from mutational catalogues
Home-page: https://github.com/AlexandrovLab/SigProfilerExtractor.git
Author: S Mishu Ashiqul Islam
Author-email: m0islam@ucsd.edu
License: UCSD
Requires-Python: >=3.9
License-File: LICENSE.txt
Requires-Dist: scipy>=1.6.3
Requires-Dist: torch>=1.8.1
Requires-Dist: numpy>=2.0.0
Requires-Dist: pandas>=2.0.0
Requires-Dist: nimfa>=1.1.0
Requires-Dist: sigProfilerPlotting>=1.4.1
Requires-Dist: SigProfilerMatrixGenerator>=1.3.5
Requires-Dist: SigProfilerAssignment>=1.1.0
Requires-Dist: statsmodels>=0.9.0
Requires-Dist: scikit-learn>=0.24.2
Requires-Dist: psutil>=5.6.1
Dynamic: author
Dynamic: author-email
Dynamic: description
Dynamic: description-content-type
Dynamic: home-page
Dynamic: license
Dynamic: license-file
Dynamic: requires-dist
Dynamic: requires-python
Dynamic: summary
